graphembed_rs-0.1.2.dist-info/METADATA
graphembed_rs-0.1.2.dist-info/WHEEL
graphembed_rs-0.1.2.dist-info/licenses/LICENSE-MIT
graphembed_rs/load_utils.py
graphembed_rs/__init__.py
graphembed_rs/graphembed_rs.cpython-39-darwin.so
graphembed_rs-0.1.2.dist-info/RECORD
