Metadata-Version: 2.4
Name: graphembed_rs
Version: 0.1.2
Requires-Dist: numpy>=2.2.5
Requires-Dist: pymongo>=4.12.1
License-File: LICENSE-MIT
Summary: Python bindings for the high‑performance Rust graph/network embedding library graphembed
Keywords: graph,embedding,hash
Author: Jianshu Zhao
Author-email: jeanpierre.both@gmail.com
License: MIT OR Apache-2.0
Requires-Python: >=3.8
Project-URL: Source Code, https://github.com/jean-pierreBoth/graphembed
